mobase-stubs/__init__.pyi
mobase-stubs/widgets/__init__.pyi
mobase_stubs-2.5.2.dist-info/METADATA
mobase_stubs-2.5.2.dist-info/WHEEL
mobase_stubs-2.5.2.dist-info/RECORD
