Metadata-Version: 2.1
Name: mobase-stubs
Version: 2.5.2
Summary: PEP561 stub files for the mobase Python API.
Home-page: https://www.modorganizer.org/python-plugins-doc/
License: MIT
Author: Holt59
Author-email: capelle.mikael@gmail.com
Requires-Python: >=3.12,<4.0
Classifier: License :: OSI Approved :: MIT License
Classifier: Programming Language :: Python :: 3
Classifier: Programming Language :: Python :: 3.12
Project-URL: Documentation, https://www.modorganizer.org/python-plugins-doc/
Project-URL: Repository, https://github.com/ModOrganizer2/mo2-pystubs-generation
